vegas-6.3.dist-info/RECORD
vegas-6.3.dist-info/WHEEL
vegas-6.3.dist-info/top_level.txt
vegas-6.3.dist-info/METADATA
vegas-6.3.dist-info/licenses/LICENSE.txt
vegas/_vegas.cpython-310-darwin.so
vegas/_version.py
vegas/__init__.pxd
vegas/__init__.py
vegas/_vegas.pyx
vegas/_vegas.pxd
vegas/_vegas.c
