Metadata-Version: 2.4
Name: vegas
Version: 6.3
Summary: Tools for adaptive multidimensional Monte Carlo integration.
Home-page: https://github.com/gplepage/vegas
Author: G. Peter Lepage
Author-email: g.p.lepage@cornell.edu
License: GPLv3
Requires-Python: >=3.9
License-File: LICENSE.txt
Requires-Dist: numpy>=1.24
Requires-Dist: gvar>=13.1.5
Dynamic: license-file
